[{"codigo":"C001","porcentajeOcupacion":70.0,"titulo":"Rock en el Parque","capacidadMaxima":5000,"asistentes":3500},{"codigo":"C002","porcentajeOcupacion":100.0,"titulo":"Jazz Nights","capacidadMaxima":850,"asistentes":850},{"codigo":"C003","porcentajeOcupacion":93.33333333333333,"titulo":"Pop Music Festival","capacidadMaxima":3000,"asistentes":2800},{"codigo":"C004","porcentajeOcupacion":87.5,"titulo":"Electro Beats Night","capacidadMaxima":4000,"asistentes":3500},{"codigo":"CF001","porcentajeOcupacion":93.33333333333333,"titulo":"Inteligencia Artificial 2024","capacidadMaxima":300,"asistentes":280},{"codigo":"CF002","porcentajeOcupacion":95.0,"titulo":"Economía Verde","capacidadMaxima":200,"asistentes":190},{"codigo":"CF003","porcentajeOcupacion":93.33333333333333,"titulo":"Blockchain y Finanzas","capacidadMaxima":150,"asistentes":140},{"codigo":"CF004","porcentajeOcupacion":96.0,"titulo":"Cambio Climático","capacidadMaxima":250,"asistentes":240}]